primalscheme3/__init__.py
primalscheme3/__main__.py
primalscheme3/cli.py
primalscheme3/core/bedfiles.py
primalscheme3/core/classes.py
primalscheme3/core/config.py
primalscheme3/core/create_report_data.py
primalscheme3/core/create_reports.py
primalscheme3/core/digestion.py
primalscheme3/core/downsample.py
primalscheme3/core/errors.py
primalscheme3/core/get_window.py
primalscheme3/core/logger.py
primalscheme3/core/mapping.py
primalscheme3/core/mismatches.py
primalscheme3/core/msa.py
primalscheme3/core/multiplex.py
primalscheme3/core/primer_visual.py
primalscheme3/core/progress_tracker.py
primalscheme3/core/seq_functions.py
primalscheme3/core/thermo.py
primalscheme3/core/thermo_misprime.py
primalscheme3/interaction/interaction.py
primalscheme3/panel/panel_classes.py
primalscheme3/panel/panel_main.py
primalscheme3/repair/repair.py
primalscheme3/replace/replace.py
primalscheme3/scheme/classes.py
primalscheme3/scheme/primer_pair_score.py
primalscheme3/scheme/scheme_main.py
primalscheme3-3.3.0.dist-info/METADATA
primalscheme3-3.3.0.dist-info/WHEEL
primalscheme3-3.3.0.dist-info/entry_points.txt
primalscheme3-3.3.0.dist-info/licenses/LICENSE
primalscheme3-3.3.0.dist-info/RECORD
