Metadata-Version: 2.4
Name: primalscheme3
Version: 3.3.0
Summary: Generation of highly multiplexed primer schemes
Project-URL: Repository, https://github.com/artic-network/primalscheme3
Author-email: ChrisKent <chrisgkent@gmail.com>
License-Expression: GPL-3.0-only
License-File: LICENSE
Requires-Python: <3.14,>=3.11
Requires-Dist: dnaio<2,>=1.2.3
Requires-Dist: kaleido==0.2.1
Requires-Dist: matplotlib<4,>=3.10.5
Requires-Dist: networkx~=3.1
Requires-Dist: numpy>=2.3.0
Requires-Dist: plotly<6,>=5.16.1
Requires-Dist: primalbedtools>=1.0.0
Requires-Dist: primalschemers<0.2,>=0.1.10
Requires-Dist: primer3-py<3,>=2.2.0
Requires-Dist: tqdm<5,>=4.66.1
Requires-Dist: typer<0.17,>=0.16.1
